{"Nodes":[],"ExecutionTime":"2022-02-02T16:39:34.5061554Z","GenerationTime":"0001-01-01T00:00:00","PluginUserSpecFlowId":"e65f363d-7f9f-4bb8-be1d-5f97d0606f53","CLIUserSpecFlowId":null,"ExecutionResults":[{"ContextType":"Scenario","FeatureFolderPath":"Features","FeatureTitle":"Login","ScenarioTitle":"Login com dados invalidos","ScenarioArguments":[],"Status":"OK","StepResults":[{"Duration":"00:00:09.5453059","Status":"OK","Error":null,"Outputs":null},{"Duration":"00:00:00.3420157","Status":"OK","Error":null,"Outputs":null},{"Duration":"00:00:00.4085556","Status":"OK","Error":null,"Outputs":null},{"Duration":"00:00:00.3415981","Status":"OK","Error":null,"Outputs":null},{"Duration":"00:00:00.3001029","Status":"OK","Error":null,"Outputs":null},{"Duration":"00:00:00.7831184","Status":"OK","Error":null,"Outputs":null}],"Outputs":null}],"StepReports":null}